<?xml version="1.0"?>
<rsp status_code="0" status_message="Success">
  <daily_counts>
    <count date="20091112T00:00:00">0</count>
    <count date="20091113T00:00:00">0</count>
    <count date="20091114T00:00:00">0</count>
    <count date="20091115T00:00:00">0</count>
    <count date="20091116T00:00:00">0</count>
    <count date="20091117T00:00:00">0</count>
    <count date="20091118T00:00:00">0</count>
    <count date="20091119T00:00:00">0</count>
    <count date="20091120T00:00:00">0</count>
    <count date="20091121T00:00:00">0</count>
    <count date="20091122T00:00:00">0</count>
    <count date="20091123T00:00:00">0</count>
    <count date="20091124T00:00:00">0</count>
    <count date="20091125T00:00:00">0</count>
    <count date="20091126T00:00:00">0</count>
    <count date="20091127T00:00:00">0</count>
    <count date="20091128T00:00:00">0</count>
    <count date="20091129T00:00:00">0</count>
    <count date="20091130T00:00:00">0</count>
    <count date="20091201T00:00:00">0</count>
    <count date="20091202T00:00:00">0</count>
    <count date="20091203T00:00:00">0</count>
    <count date="20091204T00:00:00">0</count>
    <count date="20091205T00:00:00">0</count>
    <count date="20091206T00:00:00">0</count>
    <count date="20091207T00:00:00">0</count>
    <count date="20091208T00:00:00">0</count>
    <count date="20091209T00:00:00">0</count>
    <count date="20091210T00:00:00">0</count>
    <count date="20091211T00:00:00">0</count>
    <count date="20091212T00:00:00">0</count>
    <count date="20091213T00:00:00">0</count>
    <count date="20091214T00:00:00">0</count>
    <count date="20091215T00:00:00">0</count>
    <count date="20091216T00:00:00">0</count>
    <count date="20091217T00:00:00">0</count>
    <count date="20091218T00:00:00">0</count>
    <count date="20091219T00:00:00">0</count>
    <count date="20091220T00:00:00">0</count>
    <count date="20091221T00:00:00">0</count>
    <count date="20091222T00:00:00">0</count>
    <count date="20091223T00:00:00">0</count>
    <count date="20091224T00:00:00">0</count>
    <count date="20091225T00:00:00">0</count>
    <count date="20091226T00:00:00">0</count>
    <count date="20091227T00:00:00">0</count>
    <count date="20091228T00:00:00">0</count>
    <count date="20091229T00:00:00">0</count>
    <count date="20091230T00:00:00">0</count>
    <count date="20091231T00:00:00">0</count>
    <count date="20100101T00:00:00">0</count>
    <count date="20100102T00:00:00">0</count>
    <count date="20100103T00:00:00">0</count>
    <count date="20100104T00:00:00">0</count>
    <count date="20100105T00:00:00">0</count>
    <count date="20100106T00:00:00">0</count>
    <count date="20100107T00:00:00">0</count>
    <count date="20100108T00:00:00">0</count>
    <count date="20100109T00:00:00">0</count>
    <count date="20100110T00:00:00">0</count>
    <count date="20100111T00:00:00">0</count>
    <count date="20100112T00:00:00">0</count>
    <count date="20100113T00:00:00">0</count>
    <count date="20100114T00:00:00">0</count>
    <count date="20100115T00:00:00">0</count>
    <count date="20100116T00:00:00">0</count>
    <count date="20100117T00:00:00">0</count>
    <count date="20100118T00:00:00">0</count>
    <count date="20100119T00:00:00">0</count>
    <count date="20100120T00:00:00">0</count>
    <count date="20100121T00:00:00">0</count>
    <count date="20100122T00:00:00">0</count>
    <count date="20100123T00:00:00">0</count>
    <count date="20100124T00:00:00">0</count>
    <count date="20100125T00:00:00">0</count>
    <count date="20100126T00:00:00">0</count>
    <count date="20100127T00:00:00">0</count>
    <count date="20100128T00:00:00">0</count>
    <count date="20100129T00:00:00">0</count>
    <count date="20100130T00:00:00">0</count>
    <count date="20100131T00:00:00">0</count>
    <count date="20100201T00:00:00">0</count>
    <count date="20100202T00:00:00">0</count>
    <count date="20100203T00:00:00">0</count>
    <count date="20100204T00:00:00">0</count>
    <count date="20100205T00:00:00">0</count>
    <count date="20100206T00:00:00">0</count>
    <count date="20100207T00:00:00">0</count>
    <count date="20100208T00:00:00">0</count>
    <count date="20100209T00:00:00">0</count>
    <count date="20100210T00:00:00">0</count>
    <count date="20100211T00:00:00">0</count>
    <count date="20100212T00:00:00">0</count>
    <count date="20100213T00:00:00">0</count>
    <count date="20100214T00:00:00">0</count>
    <count date="20100215T00:00:00">0</count>
    <count date="20100216T00:00:00">0</count>
    <count date="20100217T00:00:00">0</count>
    <count date="20100218T00:00:00">0</count>
    <count date="20100219T00:00:00">0</count>
    <count date="20100220T00:00:00">0</count>
    <count date="20100221T00:00:00">0</count>
    <count date="20100222T00:00:00">0</count>
    <count date="20100223T00:00:00">0</count>
    <count date="20100224T00:00:00">0</count>
    <count date="20100225T00:00:00">0</count>
    <count date="20100226T00:00:00">0</count>
    <count date="20100227T00:00:00">0</count>
    <count date="20100228T00:00:00">0</count>
    <count date="20100301T00:00:00">0</count>
    <count date="20100302T00:00:00">0</count>
    <count date="20100303T00:00:00">0</count>
    <count date="20100304T00:00:00">0</count>
    <count date="20100305T00:00:00">0</count>
    <count date="20100306T00:00:00">0</count>
    <count date="20100307T00:00:00">0</count>
    <count date="20100308T00:00:00">0</count>
    <count date="20100309T00:00:00">0</count>
    <count date="20100310T00:00:00">0</count>
    <count date="20100311T00:00:00">0</count>
  </daily_counts>
</rsp>
